matmodel/LICENSE
matmodel/README.md
matmodel/__init__.py
matmodel/base/Aspect.py
matmodel/base/MultipleAspectSequence.py
matmodel/base/__init__.py
matmodel/comparator/__init__.py
matmodel/comparator/distance.py
matmodel/comparator/helper.py
matmodel/descriptor/__init__.py
matmodel/descriptor/descriptor.py
matmodel/evaluation/Quality.py
matmodel/evaluation/__init__.py
matmodel/feature/Feature.py
matmodel/feature/Movelet.py
matmodel/feature/__init__.py
matmodel/index/__init__.py
matmodel/representative/__init__.py
matmodel/representative/representative.py
matmodel/util/__init__.py
matmodel/util/filters.py
matmodel/util/parsers.py
mat_model-0.2b1.dist-info/LICENSE
mat_model-0.2b1.dist-info/METADATA
mat_model-0.2b1.dist-info/WHEEL
mat_model-0.2b1.dist-info/top_level.txt
mat_model-0.2b1.dist-info/RECORD
