Metadata-Version: 2.2
Name: mat-model
Version: 0.2b1
Summary: MAT-model: Model Classes for Multiple Aspect Trajectory Data Mining
Home-page: https://github.com/ttportela/mat-model
Author: Tarlis Tortelli Portela
Author-email: Tarlis Tortelli Portela <tarlis@tarlis.com.br>, Vanessa Lago Machado <vanessalagomachado@gmail.com>
Maintainer-email: Tarlis Tortelli Portela <tarlis@tarlis.com.br>, Vanessa Lago Machado <vanessalagomachado@gmail.com>
License: GPL Version 3 or superior (see LICENSE file)
Project-URL: Homepage, https://github.com/ttportela/mat-model
Project-URL: Repository, https://github.com/ttportela/mat-model
Project-URL: Documentation, https://mat-analysis.github.io/mat-tools/mat-model/index.html
Project-URL: Download, https://pypi.org/project/mat-model/#files
Project-URL: Bug Tracker, https://github.com/ttportela/mat-model/issues
Keywords: data-science,machine-learning,data-mining,trajectory,multiple-trajectory,trajectory-classification,preprocess
Classifier: Intended Audience :: Science/Research
Classifier: Intended Audience :: Developers
Classifier: License :: OSI Approved :: GNU General Public License v3 or later (GPLv3+)
Classifier: Programming Language :: Python
Classifier: Topic :: Software Development
Classifier: Topic :: Scientific/Engineering
Classifier: Topic :: Scientific/Engineering :: Artificial Intelligence
Classifier: Topic :: Scientific/Engineering :: Information Analysis
Classifier: Topic :: Scientific/Engineering :: Visualization
Classifier: Operating System :: OS Independent
Classifier: Operating System :: Microsoft :: Windows
Classifier: Operating System :: POSIX
Classifier: Operating System :: Unix
Classifier: Operating System :: MacOS
Classifier: Programming Language :: Python :: 3.10
Requires-Python: >=3.7
License-File: LICENSE
Requires-Dist: glob2
Requires-Dist: numpy
Requires-Dist: pandas
Provides-Extra: all-extras
Requires-Dist: geohash; extra == "all-extras"
Provides-Extra: dev
Requires-Dist: pre-commit; extra == "dev"
Requires-Dist: pytest; extra == "dev"
Requires-Dist: pytest-cov; extra == "dev"
Requires-Dist: pytest-xdist; extra == "dev"
Requires-Dist: wheel; extra == "dev"
Provides-Extra: binder
Requires-Dist: jupyter; extra == "binder"
Provides-Extra: docs
Requires-Dist: jupyter; extra == "docs"
Requires-Dist: numpydoc; extra == "docs"
Dynamic: author
Dynamic: home-page
